orbis/__init__.py
orbis/cli.py
orbis/api/__init__.py
orbis/api/houston.py
orbis/api/prometheus.py
orbis/config/__init__.py
orbis/config/csv_template.csv
orbis/config/sa_and_role_binding.yaml
orbis/config/scanner_job.yaml
orbis/config/settings.py
orbis/data/__init__.py
orbis/data/models.py
orbis/data/transform.py
orbis/report/__init__.py
orbis/report/csv_generator.py
orbis/report/generator.py
orbis/report/visualizer.py
orbis/report/csv/__init__.py
orbis/report/csv/metrics.py
orbis/report/csv/pods.py
orbis/report/csv/processing.py
orbis/report/csv/queues.py
orbis/report/csv/templates.py
orbis/report/document/__init__.py
orbis/report/document/docx.py
orbis/report/metrics/__init__.py
orbis/report/metrics/collector.py
orbis/report/metrics/k8s_queries.py
orbis/report/metrics/query_types.py
orbis/report/metrics/query_validation.py
orbis/scanner/__init__.py
orbis/scanner/k8s_client.py
orbis/scanner/models.py
orbis/scanner/service.py
orbis/scanner/yaml_generator.py
orbis/scanner/kubernetes/__init__.py
orbis/scanner/kubernetes/cleanup.py
orbis/scanner/kubernetes/connection.py
orbis/scanner/kubernetes/file_transfer.py
orbis/scanner/kubernetes/job.py
orbis/scanner/kubernetes/pod.py
orbis/scanner/kubernetes/rbac.py
orbis/utils/__init__.py
orbis/utils/fileio.py
orbis/utils/logger.py
orbis/utils/template.py
orbis/config/houston_queries.yaml
orbis/config/prometheus_queries.yaml
astronomer_orbis-0.8.0rc13.dist-info/METADATA
astronomer_orbis-0.8.0rc13.dist-info/WHEEL
astronomer_orbis-0.8.0rc13.dist-info/entry_points.txt
astronomer_orbis-0.8.0rc13.dist-info/licenses/LICENSE
astronomer_orbis-0.8.0rc13.dist-info/RECORD
