Metadata-Version: 2.4
Name: astronomer-orbis
Version: 0.8.0rc13
Summary: A tool for generating astronomer software deployment compute reports
Project-URL: Homepage, https://github.com/astronomer/orbis
Project-URL: Bug Tracker, https://github.com/astronomer/orbis/issues
Author-email: Astronomer <humans@astronomer.io>, Abhishek Bhakat <abhishek.bhakat@astronomer.io>, Indraneel Dongaonkar <indraneel.dongaonkar@astronomer.io>, Sudarshan Chaudhari <sudarshan.chaudhari@astronomer.io>
License-File: LICENSE
Classifier: Development Status :: 4 - Beta
Classifier: Intended Audience :: Developers
Classifier: Operating System :: OS Independent
Classifier: Programming Language :: Python :: 3
Classifier: Programming Language :: Python :: 3.10
Classifier: Programming Language :: Python :: 3.11
Classifier: Programming Language :: Python :: 3.12
Classifier: Programming Language :: Python :: 3.13
Requires-Python: >=3.10
Requires-Dist: click==8.2.1
Requires-Dist: jinja2==3.1.6
Requires-Dist: kaleido==1.0.0
Requires-Dist: kubernetes==33.1.0
Requires-Dist: pendulum==3.1.0
Requires-Dist: pillow==11.3.0
Requires-Dist: plotly==6.2.0
Requires-Dist: polars==1.31.0
Requires-Dist: python-docx==1.2.0
Requires-Dist: python-dotenv==1.1.1
Requires-Dist: pyyaml==6.0.2
Requires-Dist: requests==2.32.4
Provides-Extra: dev
Requires-Dist: hatch==1.14.1; extra == 'dev'
Requires-Dist: pre-commit==4.2.0; extra == 'dev'
Requires-Dist: pytest-asyncio==1.0.0; extra == 'dev'
Requires-Dist: pytest-cov==6.2.1; extra == 'dev'
Requires-Dist: pytest-mock==3.14.1; extra == 'dev'
Requires-Dist: pytest==8.4.1; extra == 'dev'
Requires-Dist: ruff==0.12.1; extra == 'dev'
Provides-Extra: docs
Requires-Dist: mkdocs-awesome-pages-plugin==2.9.3; extra == 'docs'
Requires-Dist: mkdocs-git-revision-date-localized-plugin==1.3.0; extra == 'docs'
Requires-Dist: mkdocs-glightbox==0.4.0; extra == 'docs'
Requires-Dist: mkdocs-macros-plugin==1.3.7; extra == 'docs'
Requires-Dist: mkdocs-material==9.6.15; extra == 'docs'
Requires-Dist: mkdocs-minify-plugin==0.8.0; extra == 'docs'
Requires-Dist: mkdocs-redirects==1.2.1; extra == 'docs'
Requires-Dist: mkdocs==1.6.1; extra == 'docs'
Requires-Dist: mkdocstrings-python==1.16.12; extra == 'docs'
Requires-Dist: mkdocstrings==0.29.1; extra == 'docs'
